odoo/addons/web_sheet_full_width/README.rst
odoo/addons/web_sheet_full_width/__init__.py
odoo/addons/web_sheet_full_width/__manifest__.py
odoo/addons/web_sheet_full_width/i18n/es.po
odoo/addons/web_sheet_full_width/i18n/web_sheet_full_width.pot
odoo/addons/web_sheet_full_width/readme/CONTRIBUTORS.rst
odoo/addons/web_sheet_full_width/readme/DESCRIPTION.rst
odoo/addons/web_sheet_full_width/static/description/icon.png
odoo/addons/web_sheet_full_width/static/description/index.html
odoo/addons/web_sheet_full_width/static/src/scss/web_sheet_full_width.scss
odoo/addons/web_sheet_full_width/templates/assets.xml
odoo13_addon_web_sheet_full_width-13.0.1.0.1.dev6.dist-info/METADATA
odoo13_addon_web_sheet_full_width-13.0.1.0.1.dev6.dist-info/WHEEL
odoo13_addon_web_sheet_full_width-13.0.1.0.1.dev6.dist-info/top_level.txt
odoo13_addon_web_sheet_full_width-13.0.1.0.1.dev6.dist-info/RECORD
